{
  "metadata": {
    "last_updated": "2025-11-03T10:28:22.508635",
    "total_staff": 52,
    "version": "2.0",
    "bot_source": "VANILLA"
  },
  "modalidades": {
    "sword": [
      {
        "Rank": "Manager",
        "Discord": "meliiigi",
        "Discord ID": "772644307072581633",
        "MC Name": "Meli",
        "Status": "Active",
        "Modalidad": "Sword",
        "Server": "[1.21+] Sword PvP Community Hispana",
        "Last Updated": "2025-11-03T10:28:01.663839"
      },
      {
        "Rank": "Manager",
        "Discord": "glamsillo_",
        "Discord ID": "834555196541108246",
        "MC Name": "AtKyrie",
        "Status": "Active",
        "Modalidad": "Sword",
        "Server": "[1.21+] Sword PvP Community Hispana",
        "Last Updated": "2025-11-03T10:28:01.670714"
      },
      {
        "Rank": "Verified Tester",
        "Discord": "kazzytsu",
        "Discord ID": "1047279643272695828",
        "MC Name": "SA | blackoxyz",
        "Status": "Active",
        "Modalidad": "Sword",
        "Server": "[1.21+] Sword PvP Community Hispana",
        "Last Updated": "2025-11-03T10:28:01.664064"
      },
      {
        "Rank": "Verified Tester",
        "Discord": "ben10_p",
        "Discord ID": "1199902619234209832",
        "MC Name": "NA | Tedze_",
        "Status": "Active",
        "Modalidad": "Sword",
        "Server": "[1.21+] Sword PvP Community Hispana",
        "Last Updated": "2025-11-03T10:28:01.667640"
      },
      {
        "Rank": "Verified Tester",
        "Discord": "pacoelpanadero",
        "Discord ID": "670534819536699395",
        "MC Name": "EU | SandraConFe",
        "Status": "Active",
        "Modalidad": "Sword",
        "Server": "[1.21+] Sword PvP Community Hispana",
        "Last Updated": "2025-11-03T10:28:01.667871"
      },
      {
        "Rank": "Verified Tester",
        "Discord": "straategy_",
        "Discord ID": "1418836026381832233",
        "MC Name": "SA | NoSolote",
        "Status": "Active",
        "Modalidad": "Sword",
        "Server": "[1.21+] Sword PvP Community Hispana",
        "Last Updated": "2025-11-03T10:28:01.668889"
      },
      {
        "Rank": "Verified Tester",
        "Discord": "frenchfries_0",
        "Discord ID": "1326703062240329908",
        "MC Name": "NA | DerekDeNanita",
        "Status": "Active",
        "Modalidad": "Sword",
        "Server": "[1.21+] Sword PvP Community Hispana",
        "Last Updated": "2025-11-03T10:28:01.669629"
      },
      {
        "Rank": "Verified Tester",
        "Discord": "diminuit2",
        "Discord ID": "1398121709726601309",
        "MC Name": "SA | Diminuit",
        "Status": "Active",
        "Modalidad": "Sword",
        "Server": "[1.21+] Sword PvP Community Hispana",
        "Last Updated": "2025-11-03T10:28:01.670934"
      },
      {
        "Rank": "Verified Tester",
        "Discord": "inksouu_",
        "Discord ID": "1287130730383671388",
        "MC Name": "EU | qvoh",
        "Status": "Active",
        "Modalidad": "Sword",
        "Server": "[1.21+] Sword PvP Community Hispana",
        "Last Updated": "2025-11-03T10:28:01.671134"
      },
      {
        "Rank": "Verified Tester",
        "Discord": "1tkyv.2",
        "Discord ID": "976163381679624212",
        "MC Name": "EU | Darexcheat2006",
        "Status": "Active",
        "Modalidad": "Sword",
        "Server": "[1.21+] Sword PvP Community Hispana",
        "Last Updated": "2025-11-03T10:28:01.671551"
      },
      {
        "Rank": "Verified Tester",
        "Discord": "kimity__",
        "Discord ID": "1367909617039970406",
        "MC Name": "NA/SA | olfd",
        "Status": "Active",
        "Modalidad": "Sword",
        "Server": "[1.21+] Sword PvP Community Hispana",
        "Last Updated": "2025-11-03T10:28:01.674968"
      }
    ],
    "nethpot": [
      {
        "Rank": "Manager",
        "Discord": "glamsillo_",
        "Discord ID": "834555196541108246",
        "MC Name": "AtKyrie",
        "Status": "Active",
        "Modalidad": "NetheritePot",
        "Server": "[1.21+] Netherite Pot Community",
        "Last Updated": "2025-11-03T10:19:04.902127"
      },
      {
        "Rank": "ScreenSharer",
        "Discord": "jxr3mii",
        "Discord ID": "1249384605811736586",
        "MC Name": "Admin | Jxr3mii",
        "Status": "Active",
        "Modalidad": "NetheritePot",
        "Server": "[1.21+] Netherite Pot Community",
        "Last Updated": "2025-11-03T10:19:04.848845"
      },
      {
        "Rank": "ScreenSharer",
        "Discord": "zkernelmode",
        "Discord ID": "1088599712090824806",
        "MC Name": "SSer | zKernel",
        "Status": "Active",
        "Modalidad": "NetheritePot",
        "Server": "[1.21+] Netherite Pot Community",
        "Last Updated": "2025-11-03T10:19:04.852083"
      },
      {
        "Rank": "Verified Tester",
        "Discord": "vrxvn",
        "Discord ID": "1343637414023004220",
        "MC Name": "SA/NA | @for help",
        "Status": "Active",
        "Modalidad": "NetheritePot",
        "Server": "[1.21+] Netherite Pot Community",
        "Last Updated": "2025-11-03T10:19:04.857619"
      },
      {
        "Rank": "Verified Tester",
        "Discord": "remisero912p9",
        "Discord ID": "620119197216669706",
        "MC Name": "SA-NA | Wafledo",
        "Status": "Active",
        "Modalidad": "NetheritePot",
        "Server": "[1.21+] Netherite Pot Community",
        "Last Updated": "2025-11-03T10:19:04.857806"
      },
      {
        "Rank": "Verified Tester",
        "Discord": "psybine.",
        "Discord ID": "766048405301887010",
        "MC Name": "NA | faabula",
        "Status": "Active",
        "Modalidad": "NetheritePot",
        "Server": "[1.21+] Netherite Pot Community",
        "Last Updated": "2025-11-03T10:19:04.865330"
      },
      {
        "Rank": "Verified Tester",
        "Discord": "shalhy",
        "Discord ID": "1106675030340944032",
        "MC Name": "NA-SA | ShaLhy_0713",
        "Status": "Active",
        "Modalidad": "NetheritePot",
        "Server": "[1.21+] Netherite Pot Community",
        "Last Updated": "2025-11-03T10:19:04.871580"
      },
      {
        "Rank": "Verified Tester",
        "Discord": "fatword",
        "Discord ID": "1241523227742830635",
        "MC Name": "SA | iFortrex",
        "Status": "Active",
        "Modalidad": "NetheritePot",
        "Server": "[1.21+] Netherite Pot Community",
        "Last Updated": "2025-11-03T10:19:04.887292"
      },
      {
        "Rank": "Verified Tester",
        "Discord": "korthz",
        "Discord ID": "447100605106749440",
        "MC Name": "! korthz",
        "Status": "Active",
        "Modalidad": "NetheritePot",
        "Server": "[1.21+] Netherite Pot Community",
        "Last Updated": "2025-11-03T10:19:04.887527"
      },
      {
        "Rank": "Verified Tester",
        "Discord": "inksouu_",
        "Discord ID": "1287130730383671388",
        "MC Name": "EU | qvoh",
        "Status": "Active",
        "Modalidad": "NetheritePot",
        "Server": "[1.21+] Netherite Pot Community",
        "Last Updated": "2025-11-03T10:19:04.904107"
      },
      {
        "Rank": "Verified Tester",
        "Discord": ".sweky",
        "Discord ID": "1212418962717941771",
        "MC Name": "Helper | Sweky",
        "Status": "Active",
        "Modalidad": "NetheritePot",
        "Server": "[1.21+] Netherite Pot Community",
        "Last Updated": "2025-11-03T10:19:04.904578"
      },
      {
        "Rank": "Verified Tester",
        "Discord": "koreanch",
        "Discord ID": "742711673046958091",
        "MC Name": "SA | K1ngmichi add eval",
        "Status": "Active",
        "Modalidad": "NetheritePot",
        "Server": "[1.21+] Netherite Pot Community",
        "Last Updated": "2025-11-03T10:19:04.906773"
      },
      {
        "Rank": "Verified Tester",
        "Discord": "urr14_",
        "Discord ID": "1044342667091394580",
        "MC Name": "NA | urExodo",
        "Status": "Active",
        "Modalidad": "NetheritePot",
        "Server": "[1.21+] Netherite Pot Community",
        "Last Updated": "2025-11-03T10:19:04.911571"
      },
      {
        "Rank": "Verified Tester",
        "Discord": "icefriohielo",
        "Discord ID": "981012292202287165",
        "MC Name": "SA/NA | Icelow_190ms GOAT",
        "Status": "Active",
        "Modalidad": "NetheritePot",
        "Server": "[1.21+] Netherite Pot Community",
        "Last Updated": "2025-11-03T10:19:04.917026"
      },
      {
        "Rank": "Verified Tester",
        "Discord": "lued123.",
        "Discord ID": "1393544377569382440",
        "MC Name": "EU-NA | LuPzii",
        "Status": "Active",
        "Modalidad": "NetheritePot",
        "Server": "[1.21+] Netherite Pot Community",
        "Last Updated": "2025-11-03T10:19:04.917720"
      },
      {
        "Rank": "Verified Tester",
        "Discord": "felixgoddd",
        "Discord ID": "1404224305373384765",
        "MC Name": "SA/NA | FelixGodd",
        "Status": "Active",
        "Modalidad": "NetheritePot",
        "Server": "[1.21+] Netherite Pot Community",
        "Last Updated": "2025-11-03T10:19:04.921764"
      },
      {
        "Rank": "Verified Tester",
        "Discord": "kimity__",
        "Discord ID": "1367909617039970406",
        "MC Name": "Helper | olfd (SA/NA)",
        "Status": "Active",
        "Modalidad": "NetheritePot",
        "Server": "[1.21+] Netherite Pot Community",
        "Last Updated": "2025-11-03T10:19:04.935099"
      }
    ],
    "crystal_vanilla": [
      {
        "Rank": "Manager",
        "Discord": "lunnny_",
        "Discord ID": "1364057781014892597",
        "MC Name": "SA | IlyLunnnaa @ 4 help",
        "Status": "Active",
        "Modalidad": "Crystal/Vanilla",
        "Server": "[1.21+] Minecraft Vanilla PvP Hispana",
        "Last Updated": "2025-11-03T10:28:22.481994"
      },
      {
        "Rank": "Manager",
        "Discord": "glamsillo_",
        "Discord ID": "834555196541108246",
        "MC Name": "AtKyrie",
        "Status": "Active",
        "Modalidad": "Crystal/Vanilla",
        "Server": "[1.21+] Minecraft Vanilla PvP Hispana",
        "Last Updated": "2025-11-03T10:28:22.495287"
      },
      {
        "Rank": "Manager",
        "Discord": "itzshadess",
        "Discord ID": "1109326202793115648",
        "MC Name": "Manager • shadens-sin teclado",
        "Status": "Active",
        "Modalidad": "Crystal/Vanilla",
        "Server": "[1.21+] Minecraft Vanilla PvP Hispana",
        "Last Updated": "2025-11-03T10:28:22.496685"
      },
      {
        "Rank": "Head Tester",
        "Discord": "lopezqui",
        "Discord ID": "715648575119294546",
        "MC Name": "AUSENTE",
        "Status": "Active",
        "Modalidad": "Crystal/Vanilla",
        "Server": "[1.21+] Minecraft Vanilla PvP Hispana",
        "Last Updated": "2025-11-03T10:28:22.477440"
      },
      {
        "Rank": "Head Tester",
        "Discord": "0uon",
        "Discord ID": "757971997354623127",
        "MC Name": "enlyyy",
        "Status": "Active",
        "Modalidad": "Crystal/Vanilla",
        "Server": "[1.21+] Minecraft Vanilla PvP Hispana",
        "Last Updated": "2025-11-03T10:28:22.502616"
      },
      {
        "Rank": "Senior Tester",
        "Discord": "scxir",
        "Discord ID": "958518412387180544",
        "MC Name": "NA | Scxir",
        "Status": "Active",
        "Modalidad": "Crystal/Vanilla",
        "Server": "[1.21+] Minecraft Vanilla PvP Hispana",
        "Last Updated": "2025-11-03T10:28:22.505287"
      },
      {
        "Rank": "Verified Tester",
        "Discord": "diusikke",
        "Discord ID": "913924891588325376",
        "MC Name": "NA | Diusikke",
        "Status": "Active",
        "Modalidad": "Crystal/Vanilla",
        "Server": "[1.21+] Minecraft Vanilla PvP Hispana",
        "Last Updated": "2025-11-03T10:28:22.480013"
      },
      {
        "Rank": "Verified Tester",
        "Discord": "dirigeanttt",
        "Discord ID": "1365371835423653958",
        "MC Name": "NA | X_FanDeAleswq_X",
        "Status": "Active",
        "Modalidad": "Crystal/Vanilla",
        "Server": "[1.21+] Minecraft Vanilla PvP Hispana",
        "Last Updated": "2025-11-03T10:28:22.481053"
      },
      {
        "Rank": "Verified Tester",
        "Discord": "lennard1230071",
        "Discord ID": "1288720523819225129",
        "MC Name": "EU | Lennard",
        "Status": "Active",
        "Modalidad": "Crystal/Vanilla",
        "Server": "[1.21+] Minecraft Vanilla PvP Hispana",
        "Last Updated": "2025-11-03T10:28:22.483875"
      },
      {
        "Rank": "Verified Tester",
        "Discord": "metemelaldqus",
        "Discord ID": "936042255599415307",
        "MC Name": "NA | SA Styffy",
        "Status": "Active",
        "Modalidad": "Crystal/Vanilla",
        "Server": "[1.21+] Minecraft Vanilla PvP Hispana",
        "Last Updated": "2025-11-03T10:28:22.485532"
      },
      {
        "Rank": "Verified Tester",
        "Discord": "pieroov_",
        "Discord ID": "858367935814828092",
        "MC Name": "EU | piero @ for test",
        "Status": "Active",
        "Modalidad": "Crystal/Vanilla",
        "Server": "[1.21+] Minecraft Vanilla PvP Hispana",
        "Last Updated": "2025-11-03T10:28:22.487813"
      },
      {
        "Rank": "Verified Tester",
        "Discord": "hku9_",
        "Discord ID": "1259172426957197316",
        "MC Name": "NA | Hku9",
        "Status": "Active",
        "Modalidad": "Crystal/Vanilla",
        "Server": "[1.21+] Minecraft Vanilla PvP Hispana",
        "Last Updated": "2025-11-03T10:28:22.491209"
      },
      {
        "Rank": "Verified Tester",
        "Discord": "dytuba",
        "Discord ID": "1232054387564875791",
        "MC Name": "dytuba @ for help",
        "Status": "Active",
        "Modalidad": "Crystal/Vanilla",
        "Server": "[1.21+] Minecraft Vanilla PvP Hispana",
        "Last Updated": "2025-11-03T10:28:22.491766"
      },
      {
        "Rank": "Verified Tester",
        "Discord": "frenchfries_0",
        "Discord ID": "1326703062240329908",
        "MC Name": "DerekDeNanita Add me ht3s or lt2",
        "Status": "Active",
        "Modalidad": "Crystal/Vanilla",
        "Server": "[1.21+] Minecraft Vanilla PvP Hispana",
        "Last Updated": "2025-11-03T10:28:22.493765"
      },
      {
        "Rank": "Verified Tester",
        "Discord": "nicoow.",
        "Discord ID": "1093732777112907777",
        "MC Name": "NA | Nicolacabra",
        "Status": "Active",
        "Modalidad": "Crystal/Vanilla",
        "Server": "[1.21+] Minecraft Vanilla PvP Hispana",
        "Last Updated": "2025-11-03T10:28:22.497294"
      },
      {
        "Rank": "Verified Tester",
        "Discord": "8mag",
        "Discord ID": "764568397388054549",
        "MC Name": "Sigmawwo",
        "Status": "Active",
        "Modalidad": "Crystal/Vanilla",
        "Server": "[1.21+] Minecraft Vanilla PvP Hispana",
        "Last Updated": "2025-11-03T10:28:22.498645"
      },
      {
        "Rank": "Verified Tester",
        "Discord": "eseweyyyy",
        "Discord ID": "753322380323192914",
        "MC Name": "NA | juanoelnoob09",
        "Status": "Active",
        "Modalidad": "Crystal/Vanilla",
        "Server": "[1.21+] Minecraft Vanilla PvP Hispana",
        "Last Updated": "2025-11-03T10:28:22.504073"
      },
      {
        "Rank": "Verified Tester",
        "Discord": "torkinzz",
        "Discord ID": "936383659198525490",
        "MC Name": "andres",
        "Status": "Active",
        "Modalidad": "Crystal/Vanilla",
        "Server": "[1.21+] Minecraft Vanilla PvP Hispana",
        "Last Updated": "2025-11-03T10:28:22.504579"
      },
      {
        "Rank": "Verified Tester",
        "Discord": "madethunder",
        "Discord ID": "755600178584485990",
        "MC Name": "NA | MadeTHUNDER",
        "Status": "Active",
        "Modalidad": "Crystal/Vanilla",
        "Server": "[1.21+] Minecraft Vanilla PvP Hispana",
        "Last Updated": "2025-11-03T10:28:22.506895"
      },
      {
        "Rank": "Verified Tester",
        "Discord": "sr_robinson",
        "Discord ID": "1008163311306670112",
        "MC Name": "gnarled",
        "Status": "Active",
        "Modalidad": "Crystal/Vanilla",
        "Server": "[1.21+] Minecraft Vanilla PvP Hispana",
        "Last Updated": "2025-11-03T10:28:22.507062"
      },
      {
        "Rank": "Verified Tester",
        "Discord": "cabezaepipe888",
        "Discord ID": "993682551518543883",
        "MC Name": "NA | amoayoperobaneada",
        "Status": "Active",
        "Modalidad": "Crystal/Vanilla",
        "Server": "[1.21+] Minecraft Vanilla PvP Hispana",
        "Last Updated": "2025-11-03T10:28:22.507632"
      }
    ]
  },
  "global_owners": [
    {
      "Rank": "Owner",
      "Discord": "tiliwilis",
      "Discord ID": "1068594443441164328",
      "MC Name": "Tilw",
      "Status": "Active",
      "Modalidad": "Global",
      "Last Updated": "2025-10-31T23:50:57.169652"
    },
    {
      "Rank": "Owner",
      "Discord": "vayju",
      "Discord ID": "823659261183262730",
      "MC Name": "Sensei",
      "Status": "Active",
      "Modalidad": "Global",
      "Last Updated": "2025-10-31T23:50:57.178234"
    },
    {
      "Rank": "Owner",
      "Discord": "bigcuts",
      "Discord ID": "1311116434604294244",
      "MC Name": "Bigcuts",
      "Status": "Active",
      "Modalidad": "Global",
      "Last Updated": "2025-10-31T23:50:57.188835"
    }
  ]
}